osqp_mkl.cpython-39-darwin.so
osqp_mkl-1.0.4.dist-info/METADATA
osqp_mkl-1.0.4.dist-info/WHEEL
osqp_mkl-1.0.4.dist-info/RECORD
