Metadata-Version: 2.1
Name: osqp-mkl
Version: 1.0.4
Summary: OSQP: The Operator Splitting QP Solver
Author: Goran Banjac
Author-Email: Bartolomeo Stellato <bartolomeo.stellato@gmail.com>, Vineet Bansal <vineetbansal@protonmail.com>, Amit Solomon <as3993@princeton.edu>, Henry Schreiner <HenrySchreinerIII@gmail.com>
Project-URL: Homepage, https://osqp.org/
Requires-Python: >=3.8
Requires-Dist: osqp>=1.0.0a0
